README.txt
setup.cfg
setup.py
bliptv/__init__.py
bliptv.reader.egg-info/PKG-INFO
bliptv.reader.egg-info/SOURCES.txt
bliptv.reader.egg-info/dependency_links.txt
bliptv.reader.egg-info/entry_points.txt
bliptv.reader.egg-info/namespace_packages.txt
bliptv.reader.egg-info/not-zip-safe
bliptv.reader.egg-info/paster_plugins.txt
bliptv.reader.egg-info/requires.txt
bliptv.reader.egg-info/top_level.txt
bliptv/reader/__init__.py
bliptv/reader/interfaces.py
bliptv/reader/show.py
bliptv/reader/tests.py