Metadata-Version: 1.0
Name: bliptv.reader
Version: 1.0
Summary: A library for reading video episodes from any blip.tv show
Home-page: http://comlounge.net
Author: Christian Scholz
Author-email: mrtopf@gmail.com
License: LGPL
Keywords: bliptv video socialnetworking socialmedia newmedia library screenscraping blip
Platform: UNKNOWN
Classifier: Programming Language :: Python
Classifier: Topic :: Software Development :: Libraries :: Python Modules
